README.md
setup.py
comgames/Reversi.py
comgames/__init__.py
comgames/game.py
comgames/main.py
comgames/utils.py
comgames/version.py
comgames.egg-info/PKG-INFO
comgames.egg-info/SOURCES.txt
comgames.egg-info/dependency_links.txt
comgames.egg-info/entry_points.txt
comgames.egg-info/requires.txt
comgames.egg-info/top_level.txt